{
    "posts": [
        {
            "id": 1,
            "title": "Welcome To The New Blog",
            "body": "Lorem ipsum dolorst amet,  Lorem ipsum dolor Lorem ipsum dolor Lorem ipsum dolor Lorem ipsum dolor",
            "tags": [
                "#webdev",
                "#coding",
                "#news"
            ]
        },
        {
            "id": 2,
            "title": "Top 5 CSS Tips",
            "body": "Lorem ipsum dolorst amet,  Lorem ipsum dolor Lorem ipsum dolor Lorem ipsum dolor Lorem ipsum dolor",
            "tags": [
                "#css",
                "#webdev",
                "#coding"
            ]
        }
    ]
}